AlgoGrade/__init__.py
AlgoGrade/adapters.py
AlgoGrade/core.py
AlgoGrade/dynamic_hull.py
AlgoGrade/graham.py
AlgoGrade/parsers.py
AlgoGrade/preparata.py
AlgoGrade/quickhull.py
tests/__init__.py
tests/adapters/__init__.py
tests/adapters/test_basic_adapters.py
tests/adapters/test_core.py
tests/adapters/test_dynamic_hull.py
tests/adapters/test_graham.py
tests/adapters/test_interlibrary_converters.py
tests/adapters/test_preparata.py
tests/adapters/test_quickhull.py
tests/answers/__init__.py
tests/answers/test_dynamic_hull.py
tests/answers/test_graham.py
tests/answers/test_preparata.py
tests/answers/test_quickhull.py
tests/graders/__init__.py
tests/graders/test_dynamic_hull.py
tests/graders/test_grade_methods.py
tests/graders/test_graham.py
tests/graders/test_mock.py
tests/graders/test_prep.py
tests/graders/test_preparata.py
tests/graders/test_quickhull.py
tests/parsers/__init__.py
tests/parsers/test_point_list_and_target_point_parser.py
tests/parsers/test_point_list_parser.py
AlgoGrade-1.1.0.dist-info/LICENSE
AlgoGrade-1.1.0.dist-info/METADATA
AlgoGrade-1.1.0.dist-info/WHEEL
AlgoGrade-1.1.0.dist-info/top_level.txt
AlgoGrade-1.1.0.dist-info/RECORD
