Metadata-Version: 2.1
Name: AlgoGrade
Version: 1.1.0
Summary: A library for automated grading of algorithm-based assignments with grading of their intermediate stages. The grading of some computational geometry assignments is provided out of the box.
Author: artandfi (Artem Fisunenko)
Author-email: artyom.fisunenko@gmail.com
Keywords: Python3,automated grading,computational geometry,convex hull,region search,geometric search,point location,proximity,closest pair,closest points
Classifier: Programming Language :: Python :: 3
Classifier: Operating System :: OS Independent
License-File: LICENSE
Requires-Dist: algogears ==1.1.2
Requires-Dist: annotated-types ==0.5.0
Requires-Dist: build ==1.2.1
Requires-Dist: colorama ==0.4.6
Requires-Dist: exceptiongroup ==1.1.1
Requires-Dist: iniconfig ==2.0.0
Requires-Dist: packaging ==23.1
Requires-Dist: pluggy ==1.2.0
Requires-Dist: pydantic ==2.0
Requires-Dist: pydantic-core ==2.0.1
Requires-Dist: pyproject-hooks ==1.0.0
Requires-Dist: pytest ==7.4.0
Requires-Dist: tomli ==2.0.1
Requires-Dist: typing-extensions ==4.8.0
